fastapi_simple_pagination/__init__.py
fastapi_simple_pagination/common.py
fastapi_simple_pagination/cursor_pagination.py
fastapi_simple_pagination/deps.py
fastapi_simple_pagination/py.typed
fastapi_simple_pagination/schemas.py
fastapi_simple_pagination-2.1.1.dist-info/METADATA
fastapi_simple_pagination-2.1.1.dist-info/WHEEL
fastapi_simple_pagination-2.1.1.dist-info/RECORD
