Metadata-Version: 2.1
Name: fastapi-simple-pagination
Version: 2.1.1
Summary: Simple and generic pagination dependencies for FastAPI.
Author: Francisco Del Roio
Author-email: francipvb@hotmail.com
Requires-Python: >=3.8.1,<4.0.0
Classifier: Programming Language :: Python :: 3
Classifier: Programming Language :: Python :: 3.9
Classifier: Programming Language :: Python :: 3.10
Classifier: Programming Language :: Python :: 3.11
Requires-Dist: fastapi (<1.0.0)
Requires-Dist: pydantic (>=2.0.0,<3.0.0)
